{
  "categories": [
    {
      "category": "兑换码",
      "keywords": [
        "universal tower defense z codes"
      ]
    },
    {
      "category": "攻略",
      "keywords": [
        "universal tower defense z beginner guide",
        "universal tower defense z noob to pro guide",
        "universal tower defense z update 4 guide",
        "universal tower defense z how to get every new unit",
        "universal tower defense z summer event guide",
        "universal tower defense z bleach units guide",
        "universal tower defense z best team",
        "universal tower defense z tier list"
      ]
    },
    {
      "category": "优化器",
      "keywords": [
        "universal tower defense z meta optimizer",
        "universal tower defense z optimizer",
        "universal tower defense z unit optimizer",
        "universal tower defense z build optimizer",
        "universal tower defense z loadout calculator"
      ]
    },
    {
      "category": "灵化",
      "keywords": [
        "universal tower defense z how to etherealize",
        "universal tower defense z what is etherealize",
        "universal tower defense z etherealize",
        "universal tower defense z etherealization shards",
        "universal tower defense z how to etherealize luffy",
        "universal tower defense z how to etherealize gojo",
        "universal tower defense z etherealize boundless",
        "universal tower defense z etherealization npc",
        "universal tower defense z why cant i etherealize luffy"
      ]
    },
    {
      "category": "索隆",
      "keywords": [
        "universal tower defense z zoro",
        "universal tower defense z how to get zoro",
        "universal tower defense z how to evolve zoro",
        "universal tower defense z zoro build",
        "universal tower defense z shiny zoro",
        "universal tower defense z zoro quest",
        "universal tower defense z zoro relic",
        "universal tower defense z zoro evo items",
        "universal tower defense z zoro fragments",
        "universal tower defense z best trait for zoro"
      ]
    },
    {
      "category": "BOSS",
      "keywords": [
        "universal tower defense z zero mortal plan",
        "universal tower defense z zero mortal plan ultra boss",
        "universal tower defense z dbz ultra boss",
        "universal tower defense z where is dbz ultra boss"
      ]
    },
    {
      "category": "活动",
      "keywords": [
        "universal tower defense z pirate blitz",
        "universal tower defense z blitz",
        "universal tower defense z blitz pass"
      ]
    }
  ]
}
